data/KD_default.json
data/WLH_mean.json
data/mass_1.mas20.txt
data/KDUQDemocratic/KDUQ_correlogram.png
data/KDUQDemocratic/0/modelErrors.json
data/KDUQDemocratic/0/parameters.json
data/KDUQDemocratic/1/modelErrors.json
data/KDUQDemocratic/1/parameters.json
data/KDUQDemocratic/10/modelErrors.json
data/KDUQDemocratic/10/parameters.json
data/KDUQDemocratic/100/modelErrors.json
data/KDUQDemocratic/100/parameters.json
data/KDUQDemocratic/101/modelErrors.json
data/KDUQDemocratic/101/parameters.json
data/KDUQDemocratic/102/modelErrors.json
data/KDUQDemocratic/102/parameters.json
data/KDUQDemocratic/103/modelErrors.json
data/KDUQDemocratic/103/parameters.json
data/KDUQDemocratic/104/modelErrors.json
data/KDUQDemocratic/104/parameters.json
data/KDUQDemocratic/105/modelErrors.json
data/KDUQDemocratic/105/parameters.json
data/KDUQDemocratic/106/modelErrors.json
data/KDUQDemocratic/106/parameters.json
data/KDUQDemocratic/107/modelErrors.json
data/KDUQDemocratic/107/parameters.json
data/KDUQDemocratic/108/modelErrors.json
data/KDUQDemocratic/108/parameters.json
data/KDUQDemocratic/109/modelErrors.json
data/KDUQDemocratic/109/parameters.json
data/KDUQDemocratic/11/modelErrors.json
data/KDUQDemocratic/11/parameters.json
data/KDUQDemocratic/110/modelErrors.json
data/KDUQDemocratic/110/parameters.json
data/KDUQDemocratic/111/modelErrors.json
data/KDUQDemocratic/111/parameters.json
data/KDUQDemocratic/112/modelErrors.json
data/KDUQDemocratic/112/parameters.json
data/KDUQDemocratic/113/modelErrors.json
data/KDUQDemocratic/113/parameters.json
data/KDUQDemocratic/114/modelErrors.json
data/KDUQDemocratic/114/parameters.json
data/KDUQDemocratic/115/modelErrors.json
data/KDUQDemocratic/115/parameters.json
data/KDUQDemocratic/116/modelErrors.json
data/KDUQDemocratic/116/parameters.json
data/KDUQDemocratic/117/modelErrors.json
data/KDUQDemocratic/117/parameters.json
data/KDUQDemocratic/118/modelErrors.json
data/KDUQDemocratic/118/parameters.json
data/KDUQDemocratic/119/modelErrors.json
jitr-2.1.2.dist-info/LICENSE
jitr-2.1.2.dist-info/METADATA
jitr-2.1.2.dist-info/WHEEL
jitr-2.1.2.dist-info/top_level.txt
jitr-2.1.2.dist-info/RECORD
