Metadata-Version: 2.2
Name: jitr
Version: 2.1.2
Summary: Calculable R-matrix solver for quantum scattering using just-in-time compilation for performance.
Author-email: Kyle Beyer <beykyle@umich.edu>
License: BSD 3-Clause License
Classifier: Programming Language :: Python :: 3
Classifier: License :: OSI Approved :: MIT License
Classifier: Operating System :: OS Independent
Requires-Python: >=3.9
License-File: LICENSE
Requires-Dist: numba>=0.59.1
Requires-Dist: numpy>=1.26.4
Requires-Dist: scipy>=1.13.0
Requires-Dist: mpmath>=1.3.0
Requires-Dist: sympy>=1.12
Requires-Dist: pandas>2.0
